pyduinobridge/__init__.py
pyduinobridge/pyduinobridge.py
python/__init__.py
python/pyduinobridge.py
pyduinobridge-1.0.7.dist-info/LICENSE
pyduinobridge-1.0.7.dist-info/METADATA
pyduinobridge-1.0.7.dist-info/WHEEL
pyduinobridge-1.0.7.dist-info/top_level.txt
pyduinobridge-1.0.7.dist-info/RECORD
