Metadata-Version: 2.1
Name: pyduinobridge
Version: 1.0.7
Summary: A transparent library for communication between Python and Arduino
Home-page: https://github.com/DanielSaromo/PyDuinoBridge
Author: Daniel Saromo
Author-email: danielsaromo@gmail.com
License: UNKNOWN
Platform: UNKNOWN
Classifier: Programming Language :: Python :: 3
Classifier: License :: OSI Approved :: Apache Software License
Classifier: Operating System :: OS Independent
Requires-Python: >=3
